yakinori/__init__.py
yakinori/test.py
yakinori/yakinori.py
yakinori-0.1.2.dist-info/LICENSE
yakinori-0.1.2.dist-info/METADATA
yakinori-0.1.2.dist-info/WHEEL
yakinori-0.1.2.dist-info/top_level.txt
yakinori-0.1.2.dist-info/RECORD
