Metadata-Version: 2.1
Name: yakinori
Version: 0.1.2
Summary: yakinori is a tool for converting Kanji to hiragana, katakana, roma-ji.
Home-page: https://github.com/morikatron/yakinori
Author: Hikaru Yamada
Author-email: hikaru.yamada@morikatron.co.jp
License: MIT
Keywords: Japanese converter,Japanese,text preprocessing,Hiragana,Katakana,Kanji,alphabet
Requires-Python: >=3.8
License-File: LICENSE
Requires-Dist: mecab-python3
Requires-Dist: jaconv
